{
    "nodes": [
        {
            "id": 0
        },
        {
            "id": 1
        },
        {
            "id": 2
        },
        {
            "id": 3
        }
    ],
    "edges": [
        {
            "from": 0,
            "to": 1,
            "capacity": 5
        },
        {
            "from": 1,
            "to": 2,
            "capacity": 5
        },
        {
            "from": 2,
            "to": 3,
            "capacity": 5
        },
        {
            "from": 1,
            "to": 3,
            "capacity": 3
        }
    ],
    "cars": [
        {
            "start_edge": 0,
            "start_position": 0,
            "fungible_start_edge": false,
            "fungible_start_position": false,
            "end_edge": 1,
            "end_position": 1,
            "fungible_end_position" : 0
        }
    ]
}